MANIFEST.in
README.rst
setup.py
Juboor_Toolbox/ML.py
Juboor_Toolbox/__init__.py
Juboor_Toolbox/plots.py
Juboor_Toolbox/stats.py
Juboor_Toolbox.egg-info/PKG-INFO
Juboor_Toolbox.egg-info/SOURCES.txt
Juboor_Toolbox.egg-info/dependency_links.txt
Juboor_Toolbox.egg-info/not-zip-safe
Juboor_Toolbox.egg-info/top_level.txt