Metadata-Version: 1.1
Name: Juboor-Toolbox
Version: 0.1.3.1
Summary: This is a compilation of the tools that I use from day-to-day
Home-page: http://github.com/Djuboor/Juboor_Toolbox
Author: David Juboor
Author-email: dnjuboor@gmail.com
License: MIT
Keywords: DavidJuboor Juboor Statistics ML MachineLearning
Platform: UNKNOWN
Classifier: Development Status :: 3 - Alpha
Classifier: License :: OSI Approved :: MIT License
Classifier: Programming Language :: Python :: 2.7
